{
  "posts": [
    {
      "id": 2,
      "title": "Quyển sách 2",
      "author": "author2"
    },
    {
      "id": "3",
      "title": "Quyển Sách 3",
      "author": "Es"
    },
    {
      "id": "4",
      "title": "Quyển sách 4",
      "author": "author4"
    },
    {
      "id": "5",
      "title": "Quyển Sách 5",
      "author": "author5"
    },
    {
      "id": "6",
      "title": "Quyển sách 6",
      "author": "author6"
    },
    {
      "id": "7",
      "title": "Quyển 7",
      "author": "author 7"
    },
    {
      "id": "8",
      "title": "Quyển sách 8",
      "author": "author8"
    }
  ]
}